[
{
  "id": "S1501_C01_054E",
  "label": "Total!!Estimate!!Hispanic or Latino Origin!!Bachelor's degree or higher",
  "concept": "EDUCATIONAL ATTAINMENT",
  "predicateType": "int",
  "group": "S1501",
  "limit": 0,
  "attributes": "S1501_C01_054M,S1501_C01_054MA,S1501_C01_054EA"
},
{
  "id": "S1501_C01_053E",
  "label": "Total!!Estimate!!Hispanic or Latino Origin!!High school graduate or higher",
  "concept": "EDUCATIONAL ATTAINMENT",
  "predicateType": "int",
  "group": "S1501",
  "limit": 0,
  "attributes": "S1501_C01_053M,S1501_C01_053MA,S1501_C01_053EA"
},
{
  "id": "B14007I_001E",
  "label": "Estimate!!Total School Enrollment Pop 3 Years and Over",
  "concept": "SCHOOL ENROLLMENT BY DETAILED LEVEL OF SCHOOL FOR THE POPULATION 3 YEARS AND OVER (HISPANIC OR LATINO)",
  "predicateType": "int",
  "group": "B14007I",
  "limit": 0,
  "attributes": "B14007I_001M,B14007I_001MA,B14007I_001EA"
},
{
  "id": "total_hispanic_pop_over_25",
  "label": "Total!!Estimate!!Hispanic or Latino Origin!!Over 25 Years Old",
  "concept": "EDUCATIONAL ATTAINMENT",
  "predicateType": "int",
  "group": "S1501",
  "limit": 0,
  "attributes": "S1501_C01_052M,S1501_C01_052MA,S1501_C01_052EA"},
{
  "id": "total_hispanic_pop_under_25",
  "label": "Total!!Estimate!!Hispanic or Latino Origin!!Under 25 Years Old",
  "concept": "EDUCATIONAL ATTAINMENT",
  "predicateType": "int",
  "group": "S1501",
  "limit": 0,
  "attributes": "S1501_C01_052M,S1501_C01_052MA,S1501_C01_052EA"},
{
  "id": "B03001_001E",
  "label": "Estimate!!Total Population in US",
  "concept": "HISPANIC OR LATINO ORIGIN BY SPECIFIC ORIGIN",
  "predicateType": "int",
  "group": "B03001",
  "limit": 0,
  "attributes": "B03001_001M,B03001_001MA,B03001_001EA"},
{
  "id": "B03001_003E",
  "label": "Estimate!!Total!!Hispanic or Latino",
  "concept": "HISPANIC OR LATINO ORIGIN BY SPECIFIC ORIGIN",
  "predicateType": "int",
  "group": "B03001",
  "limit": 0,
  "attributes": "B03001_003M,B03001_003MA,B03001_003EA"},
{
  "id": "B03002_003E",
  "label": "Estimate!!Total!!Not Hispanic or Latino!!White alone",
  "concept": "HISPANIC OR LATINO ORIGIN BY RACE",
  "predicateType": "int",
  "group": "B03002",
  "limit": 0,
  "attributes": "B03002_003M,B03002_003MA,B03002_003EA"},
{
  "id": "B03002_004E",
  "label": "Estimate!!Total!!Not Hispanic or Latino!!Black or African American alone",
  "concept": "HISPANIC OR LATINO ORIGIN BY RACE",
  "predicateType": "int",
  "group": "B03002",
  "limit": 0,
  "attributes": "B03002_004M,B03002_004MA,B03002_004EA"},
{
  "id": "B03002_006E",
  "label": "Estimate!!Total!!Not Hispanic or Latino!!Asian alone",
  "concept": "HISPANIC OR LATINO ORIGIN BY RACE",
  "predicateType": "int",
  "group": "B03002",
  "limit": 0,
  "attributes": "B03002_006M,B03002_006MA,B03002_006EA"},
{
  "id":"DP02_0059PE",
  "concept":"SELECTED SOCIAL CHARACTERISTICS IN THE UNITED STATES",
  "label":"EDUCATIONAL ATTAINMENT!!Population 25 years and over!!Less than 9th grade"},
{
  "id":"DP02_0060PE",
  "concept":"SELECTED SOCIAL CHARACTERISTICS IN THE UNITED STATES",
  "label":"EDUCATIONAL ATTAINMENT!!Population 25 years and over!!9th to 12th grade, no diploma"},
{
  "id":"DP02_0064PE",
  "concept":"SELECTED SOCIAL CHARACTERISTICS IN THE UNITED STATES",
  "label":"EDUCATIONAL ATTAINMENT!!Population 25 years and over!!Bachelor's degree"},
{
  "id":"DP02_0065PE",
  "concept":"SELECTED SOCIAL CHARACTERISTICS IN THE UNITED STATES",
  "label":"EDUCATIONAL ATTAINMENT!!Population 25 years and over!!Graduate or professional degree"},
{
  "id":"DP02_0067PE",
  "concept":"SELECTED SOCIAL CHARACTERISTICS IN THE UNITED STATES",
  "label":"EDUCATIONAL ATTAINMENT!!Population 25 years and over!!Percent bachelor's degree or higher"},
{
  "id":"DP05_0033PE",
  "concept":"ACS DEMOGRAPHIC AND HOUSING ESTIMATES",
  "label":"RACE!!One race!!Black or African American"},
{
  "id":"DP05_0039PE",
  "concept":"ACS DEMOGRAPHIC AND HOUSING ESTIMATES",
  "label":"RACE!!One race!!Asian"},
{
  "id":"DP05_0032PE",
  "concept":"ACS DEMOGRAPHIC AND HOUSING ESTIMATES",
  "label":"RACE!!One race!!White"},
{
  "id":"DP05_0066PE",
  "concept":"ACS DEMOGRAPHIC AND HOUSING ESTIMATES",
  "label":"HISPANIC OR LATINO AND RACE!!Total population!!Hispanic or Latino (of any race)"},
{
  "id": "DP02_0122E",
  "label": "ANCESTRY!!Total population",
  "concept": "SELECTED SOCIAL CHARACTERISTICS IN THE UNITED STATES",
  "group": "N/A",
  "limit": 0},
{
  "id": "B14007I_017E",
  "label": "Estimate!!Total!!Enrolled in school Hispanic!!Enrolled in college, undergraduate years",
  "concept": "SCHOOL ENROLLMENT BY DETAILED LEVEL OF SCHOOL FOR THE POPULATION 3 YEARS AND OVER (HISPANIC OR LATINO)",
  "predicateType": "int",
  "group": "B14007I",
  "limit": 0,
  "attributes": "B14007I_017M,B14007I_017MA,B14007I_017EA"},
{
  "id": "B14007H_017E",
  "label": "Estimate!!Total!!Enrolled in school White!!Enrolled in college, undergraduate years",
  "concept": "SCHOOL ENROLLMENT BY DETAILED LEVEL OF SCHOOL FOR THE POPULATION 3 YEARS AND OVER (WHITE ALONE, NOT HISPANIC OR LATINO)",
  "predicateType": "int",
  "group": "B14007H",
  "limit": 0,
  "attributes": "B14007H_017M,B14007H_017MA,B14007H_017EA"},
{
  "id": "DP05_0072PE",
  "label": "HISPANIC OR LATINO AND RACE!!Total population!!Not Hispanic or Latino!!White alone",
  "concept": "ACS DEMOGRAPHIC AND HOUSING ESTIMATES",
  "predicateType": "int",
  "group": "N/A",
  "limit": 0},
{
  "id": "C15010H_001E",
  "label": "Estimate!!Total!!Bachelor's Degree, Population >=25 (White, Not Hispanic)",
  "concept": "FIELD OF BACHELOR'S DEGREE FOR FIRST MAJOR THE POPULATION 25 YEARS AND OVER (WHITE ALONE, NOT HISPANIC OR LATINO)",
  "predicateType": "int",
  "group": "C15010H",
  "limit": 0,
  "attributes": "C15010H_001M,C15010H_001MA,C15010H_001EA"},
{
  "id": "C15010I_003E",
  "label": "Estimate!!Total!!Science and Engineering Related Fields!!Bachelor's Degree, Population >=25 (Hispanic)",
  "concept": "FIELD OF BACHELOR'S DEGREE FOR FIRST MAJOR THE POPULATION 25 YEARS AND OVER (HISPANIC OR LATINO)",
  "predicateType": "int",
  "group": "C15010I",
  "limit": 0,
  "attributes": "C15010I_003M,C15010I_003MA,C15010I_003EA"},
{
  "id": "C15010I_004E",
  "label": "Estimate!!Total!!Business!!Bachelor's Degree, Population >=25 (Hispanic)",
  "concept": "FIELD OF BACHELOR'S DEGREE FOR FIRST MAJOR THE POPULATION 25 YEARS AND OVER (HISPANIC OR LATINO)",
  "predicateType": "int",
  "group": "C15010I",
  "limit": 0,
  "attributes": "C15010I_004M,C15010I_004MA,C15010I_004EA"},
{
  "id": "C15010_001E",
  "label": "Estimate!!Total!!Bachelor's Degree, Population >=25",
  "concept": "FIELD OF BACHELOR'S DEGREE FOR FIRST MAJOR FOR THE POPULATION 25 YEARS AND OVER",
  "predicateType": "int",
  "group": "C15010",
  "limit": 0,
  "attributes": "C15010_001M,C15010_001MA,C15010_001EA"},
{
  "id": "C15002I_001E",
  "label": "Estimate!!Total!!Educational Attainment, Population >=25 (Hispanic)",
  "concept": "SEX BY EDUCATIONAL ATTAINMENT FOR THE POPULATION 25 YEARS AND OVER (HISPANIC OR LATINO)",
  "predicateType": "int",
  "group": "C15002I",
  "limit": 0,
  "attributes": "C15002I_001M,C15002I_001MA,C15002I_001EA"},
{
  "id": "C15002H_001E",
  "label": "Estimate!!Total!!Educational Attainment, Population >=25 (White, Not Hispanic)",
  "concept": "SEX BY EDUCATIONAL ATTAINMENT FOR THE POPULATION 25 YEARS AND OVER (WHITE ALONE, NOT HISPANIC OR LATINO)",
  "predicateType": "int",
  "group": "C15002H",
  "limit": 0,
  "attributes": "C15002H_001M,C15002H_001MA,C15002H_001EA"},
{
  "id": "C15002A_001E",
  "label": "Estimate!!Total!!Educational Attainment, Population >=25 (White)",
  "concept": "SEX BY EDUCATIONAL ATTAINMENT FOR THE POPULATION 25 YEARS AND OVER (WHITE ALONE)",
  "predicateType": "int",
  "group": "C15002A",
  "limit": 0,
  "attributes": "C15002A_001M,C15002A_001MA,C15002A_001EA"},
{
  "id": "C15010I_001E",
  "label": "Estimate!!Total!!Bachelor's Degree, Population >=25 (Hispanic)",
  "concept": "FIELD OF BACHELOR'S DEGREE FOR FIRST MAJOR THE POPULATION 25 YEARS AND OVER (HISPANIC OR LATINO)",
  "predicateType": "int",
  "group": "C15010I",
  "limit": 0,
  "attributes": "C15010I_001M,C15010I_001MA,C15010I_001EA"
}]
